{"type": "Topology", "objects": {"data": {"geometries": [{"type": "Polygon", "properties": {"ID": 15171, "CD_GEOCODI": "411520005430001", "TIPO": "URBANO", "CD_GEOCODB": "411520005103", "NM_BAIRRO": "Conjunto Residencial Ney Braga", "CD_GEOCODS": "41152000543", "NM_SUBDIST": "ZONA 43", "CD_GEOCODD": "411520005", "NM_DISTRIT": "MARING\u00c1", "CD_GEOCODM": "4115200", "NM_MUNICIP": "MARING\u00c1", "NM_MICRO": "MARING\u00c1", "NM_MESO": "NORTE CENTRAL PARANAENSE", "smartlab_geo_id": "411520005430001"}, "arcs": [[0, -24, -2, -5]]}, {"type": "Polygon", "properties": {"ID": 15172, "CD_GEOCODI": "411520005430002", "TIPO": "URBANO", "CD_GEOCODB": "411520005103", "NM_BAIRRO": "Conjunto Residencial Ney Braga", "CD_GEOCODS": "41152000543", "NM_SUBDIST": "ZONA 43", "CD_GEOCODD": "411520005", "NM_DISTRIT": "MARING\u00c1", "CD_GEOCODM": "4115200", "NM_MUNICIP": "MARING\u00c1", "NM_MICRO": "MARING\u00c1", "NM_MESO": "NORTE CENTRAL PARANAENSE", "smartlab_geo_id": "411520005430002"}, "arcs": [[-6, 1, -23, 2, -9]]}, {"type": "Polygon", "properties": {"ID": 15173, "CD_GEOCODI": "411520005430003", "TIPO": "URBANO", "CD_GEOCODB": "411520005103", "NM_BAIRRO": "Conjunto Residencial Ney Braga", "CD_GEOCODS": "41152000543", "NM_SUBDIST": "ZONA 43", "CD_GEOCODD": "411520005", "NM_DISTRIT": "MARING\u00c1", "CD_GEOCODM": "4115200", "NM_MUNICIP": "MARING\u00c1", "NM_MICRO": "MARING\u00c1", "NM_MESO": "NORTE CENTRAL PARANAENSE", "smartlab_geo_id": "411520005430003"}, "arcs": [[3, 4, 5, -8, -42, 6]]}, {"type": "Polygon", "properties": {"ID": 15174, "CD_GEOCODI": "411520005430004", "TIPO": "URBANO", "CD_GEOCODB": "411520005103", "NM_BAIRRO": "Conjunto Residencial Ney Braga", "CD_GEOCODS": "41152000543", "NM_SUBDIST": "ZONA 43", "CD_GEOCODD": "411520005", "NM_DISTRIT": "MARING\u00c1", "CD_GEOCODM": "4115200", "NM_MUNICIP": "MARING\u00c1", "NM_MICRO": "MARING\u00c1", "NM_MESO": "NORTE CENTRAL PARANAENSE", "smartlab_geo_id": "411520005430004"}, "arcs": [[-43, 7, 8, 9, -13]]}, {"type": "Polygon", "properties": {"ID": 15175, "CD_GEOCODI": "411520005430005", "TIPO": "URBANO", "CD_GEOCODB": "411520005104", "NM_BAIRRO": "Conjunto Habitacional SANENGE", "CD_GEOCODS": "41152000543", "NM_SUBDIST": "ZONA 43", "CD_GEOCODD": "411520005", "NM_DISTRIT": "MARING\u00c1", "CD_GEOCODM": "4115200", "NM_MUNICIP": "MARING\u00c1", "NM_MICRO": "MARING\u00c1", "NM_MESO": "NORTE CENTRAL PARANAENSE", "smartlab_geo_id": "411520005430005"}, "arcs": [[10, -17, -29]]}, {"type": "Polygon", "properties": {"ID": 15176, "CD_GEOCODI": "411520005430006", "TIPO": "URBANO", "CD_GEOCODB": "411520005105", "NM_BAIRRO": "Parque Hort\u00eancia I", "CD_GEOCODS": "41152000543", "NM_SUBDIST": "ZONA 43", "CD_GEOCODD": "411520005", "NM_DISTRIT": "MARING\u00c1", "CD_GEOCODM": "4115200", "NM_MUNICIP": "MARING\u00c1", "NM_MICRO": "MARING\u00c1", "NM_MESO": "NORTE CENTRAL PARANAENSE", "smartlab_geo_id": "411520005430006"}, "arcs": [[-15, -19, -37, -31, -16]]}, {"type": "Polygon", "properties": {"ID": 15177, "CD_GEOCODI": "411520005430007", "TIPO": "URBANO", "CD_GEOCODB": "", "NM_BAIRRO": "", "CD_GEOCODS": "41152000543", "NM_SUBDIST": "ZONA 43", "CD_GEOCODD": "411520005", "NM_DISTRIT": "MARING\u00c1", "CD_GEOCODM": "4115200", "NM_MUNICIP": "MARING\u00c1", "NM_MICRO": "MARING\u00c1", "NM_MESO": "NORTE CENTRAL PARANAENSE", "smartlab_geo_id": "411520005430007"}, "arcs": [[11, -44, 12, 13, 14, 15, -30, 16]]}, {"type": "Polygon", "properties": {"ID": 15178, "CD_GEOCODI": "411520005430008", "TIPO": "URBANO", "CD_GEOCODB": "", "NM_BAIRRO": "", "CD_GEOCODS": "41152000543", "NM_SUBDIST": "ZONA 43", "CD_GEOCODD": "411520005", "NM_DISTRIT": "MARING\u00c1", "CD_GEOCODM": "4115200", "NM_MUNICIP": "MARING\u00c1", "NM_MICRO": "MARING\u00c1", "NM_MESO": "NORTE CENTRAL PARANAENSE", "smartlab_geo_id": "411520005430008"}, "arcs": [[17, -26, -38, 18, 19, -33, 20]]}, {"type": "Polygon", "properties": {"ID": 15179, "CD_GEOCODI": "411520005430009", "TIPO": "URBANO", "CD_GEOCODB": "", "NM_BAIRRO": "", "CD_GEOCODS": "41152000543", "NM_SUBDIST": "ZONA 43", "CD_GEOCODD": "411520005", "NM_DISTRIT": "MARING\u00c1", "CD_GEOCODM": "4115200", "NM_MUNICIP": "MARING\u00c1", "NM_MICRO": "MARING\u00c1", "NM_MESO": "NORTE CENTRAL PARANAENSE", "smartlab_geo_id": "411520005430009"}, "arcs": [[21, 22, 23]]}, {"type": "Polygon", "properties": {"ID": 15180, "CD_GEOCODI": "411520005430010", "TIPO": "URBANO", "CD_GEOCODB": "", "NM_BAIRRO": "", "CD_GEOCODS": "41152000543", "NM_SUBDIST": "ZONA 43", "CD_GEOCODD": "411520005", "NM_DISTRIT": "MARING\u00c1", "CD_GEOCODM": "4115200", "NM_MUNICIP": "MARING\u00c1", "NM_MICRO": "MARING\u00c1", "NM_MESO": "NORTE CENTRAL PARANAENSE", "smartlab_geo_id": "411520005430010"}, "arcs": [[24, -39, 25, 26]]}, {"type": "Polygon", "properties": {"ID": 15181, "CD_GEOCODI": "411520005430011", "TIPO": "URBANO", "CD_GEOCODB": "411520005105", "NM_BAIRRO": "Parque Hort\u00eancia I", "CD_GEOCODS": "41152000543", "NM_SUBDIST": "ZONA 43", "CD_GEOCODD": "411520005", "NM_DISTRIT": "MARING\u00c1", "CD_GEOCODM": "4115200", "NM_MUNICIP": "MARING\u00c1", "NM_MICRO": "MARING\u00c1", "NM_MESO": "NORTE CENTRAL PARANAENSE", "smartlab_geo_id": "411520005430011"}, "arcs": [[27, 28, 29, 30, -36]]}, {"type": "Polygon", "properties": {"ID": 15182, "CD_GEOCODI": "411520005430012", "TIPO": "URBANO", "CD_GEOCODB": "", "NM_BAIRRO": "", "CD_GEOCODS": "41152000543", "NM_SUBDIST": "ZONA 43", "CD_GEOCODD": "411520005", "NM_DISTRIT": "MARING\u00c1", "CD_GEOCODM": "4115200", "NM_MUNICIP": "MARING\u00c1", "NM_MICRO": "MARING\u00c1", "NM_MESO": "NORTE CENTRAL PARANAENSE", "smartlab_geo_id": "411520005430012"}, "arcs": [[31, 32, 33]]}, {"type": "Polygon", "properties": {"ID": 15183, "CD_GEOCODI": "411520005430013", "TIPO": "URBANO", "CD_GEOCODB": "", "NM_BAIRRO": "", "CD_GEOCODS": "41152000543", "NM_SUBDIST": "ZONA 43", "CD_GEOCODD": "411520005", "NM_DISTRIT": "MARING\u00c1", "CD_GEOCODM": "4115200", "NM_MUNICIP": "MARING\u00c1", "NM_MICRO": "MARING\u00c1", "NM_MESO": "NORTE CENTRAL PARANAENSE", "smartlab_geo_id": "411520005430013"}, "arcs": [[34, 35, 36, 37, 38, 39]]}, {"type": "Polygon", "properties": {"ID": 15184, "CD_GEOCODI": "411520005430014", "TIPO": "URBANO", "CD_GEOCODB": "411520005103", "NM_BAIRRO": "Conjunto Residencial Ney Braga", "CD_GEOCODS": "41152000543", "NM_SUBDIST": "ZONA 43", "CD_GEOCODD": "411520005", "NM_DISTRIT": "MARING\u00c1", "CD_GEOCODM": "4115200", "NM_MUNICIP": "MARING\u00c1", "NM_MICRO": "MARING\u00c1", "NM_MESO": "NORTE CENTRAL PARANAENSE", "smartlab_geo_id": "411520005430014"}, "arcs": [[40, 41, 42, 43]]}], "type": "GeometryCollection"}}, "bbox": [-51.980466, -23.424751, -51.958799, -23.387213], "arcs": [[[-51.970307999999996, -23.391479], [-51.96921, -23.390054]], [[-51.967811999999995, -23.393407], [-51.966606999999996, -23.39211]], [[-51.964158999999995, -23.393572], [-51.965287, -23.396608]], [[-51.971084999999995, -23.392366], [-51.970307999999996, -23.391479]], [[-51.970307999999996, -23.391479], [-51.967811999999995, -23.393407]], [[-51.967811999999995, -23.393407], [-51.968578, -23.394268]], [[-51.9714702642694, -23.392816140377], [-51.971084999999995, -23.392366]], [[-51.9689568645373, -23.394687981618898], [-51.968578, -23.394268]], [[-51.968578, -23.394268], [-51.965287, -23.396608]], [[-51.965287, -23.396608], [-51.966587999999994, -23.398985]], [[-51.974692999999995, -23.396327], [-51.973332, -23.394807999999998]], [[-51.973332, -23.394807999999998], [-51.973006999999996, -23.394477]], [[-51.970231, -23.396105], [-51.966587999999994, -23.398985]], [[-51.966587999999994, -23.398985], [-51.967721999999995, -23.401398]], [[-51.967721999999995, -23.401398], [-51.968416999999995, -23.400966]], [[-51.968416999999995, -23.400966], [-51.971333654610895, -23.398976229984797]], [[-51.971784, -23.398668999999998], [-51.973332, -23.394807999999998]], [[-51.979623, -23.419138], [-51.974244, -23.407519999999998]], [[-51.970779, -23.402881], [-51.967721999999995, -23.401398]], [[-51.967721999999995, -23.401398], [-51.9637300346556, -23.412223391936298]], [[-51.9633969732571, -23.413094416570697], [-51.979623, -23.419138]], [[-51.96921, -23.390054], [-51.964158999999995, -23.393572]], [[-51.964158999999995, -23.393572], [-51.966606999999996, -23.39211]], [[-51.966606999999996, -23.39211], [-51.96921, -23.390054]], [[-51.980466, -23.402547], [-51.978263905858896, -23.400148549189]], [[-51.9724159064848, -23.4046534104954], [-51.974244, -23.407519999999998]], [[-51.974244, -23.407519999999998], [-51.980466, -23.402547]], [[-51.976518, -23.398270999999998], [-51.974692999999995, -23.396327]], [[-51.974692999999995, -23.396327], [-51.971784, -23.398668999999998]], [[-51.971784, -23.398668999999998], [-51.971333654610895, -23.398976229984797]], [[-51.971333654610895, -23.398976229984797], [-51.9742248638708, -23.4001155169051]], [[-51.963724, -23.412235], [-51.9633969732571, -23.413094416570697]], [[-51.9633969732571, -23.413094416570697], [-51.9637300346556, -23.412223391936298]], [[-51.9637300346556, -23.412223391936298], [-51.963724, -23.412235]], [[-51.978001, -23.399865], [-51.976518, -23.398270999999998]], [[-51.976518, -23.398270999999998], [-51.9742248638708, -23.4001155169051]], [[-51.9742248638708, -23.4001155169051], [-51.970779, -23.402881]], [[-51.970779, -23.402881], [-51.9724159064848, -23.4046534104954]], [[-51.9724159064848, -23.4046534104954], [-51.978263905858896, -23.400148549189]], [[-51.978263905858896, -23.400148549189], [-51.978001, -23.399865]], [[-51.973006999999996, -23.394477], [-51.9714702642694, -23.392816140377]], [[-51.9714702642694, -23.392816140377], [-51.9689568645373, -23.394687981618898]], [[-51.9689568645373, -23.394687981618898], [-51.970231, -23.396105]], [[-51.970231, -23.396105], [-51.973006999999996, -23.394477]]]}